xiuxian_boss/__init__.py
xiuxian_boss/bossconfig.py
xiuxian_boss/makeboss.py
xiuxian_boss/old_boss_info.py
xiuxian_boss-0.30.dist-info/METADATA
xiuxian_boss-0.30.dist-info/WHEEL
xiuxian_boss-0.30.dist-info/top_level.txt
xiuxian_boss-0.30.dist-info/RECORD
